emailuser/__init__.py
emailuser/admin.py
emailuser/apps.py
emailuser/forms.py
emailuser/managers.py
emailuser/models.py
emailuser/permissions.py
emailuser/serializers.py
emailuser/urls.py
emailuser/views.py
emailuser/migrations/0001_initial.py
emailuser/migrations/__init__.py
djangorestframework_emailuser-0.3.1.dev0.dist-info/LICENSE
djangorestframework_emailuser-0.3.1.dev0.dist-info/WHEEL
djangorestframework_emailuser-0.3.1.dev0.dist-info/METADATA
djangorestframework_emailuser-0.3.1.dev0.dist-info/RECORD
