Metadata-Version: 2.1
Name: djangorestframework_emailuser
Version: 0.3.1.dev0
Summary: A user for djangorestframework that uses an email as the username.
Keywords: django,djangorestframework,drf,user,emailuser
Author-email: MS List <simlist@gmail.com>
Requires-Python: >=3.7
Classifier: Development Status :: 4 - Beta
Classifier: Intended Audience :: Developers
Classifier: Topic :: Software Development :: Libraries :: Python Modules
Classifier: Environment :: Web Environment
Classifier: Framework :: Django
Classifier: License :: OSI Approved :: MIT License
Classifier: Programming Language :: Python :: 3
Classifier: Programming Language :: Python :: 3 :: Only
Classifier: Programming Language :: Python :: 3.7
Classifier: Programming Language :: Python :: 3.8
Classifier: Programming Language :: Python :: 3.9
Classifier: Programming Language :: Python :: 3.10
Classifier: Programming Language :: Python :: 3.11
Requires-Dist: django >= 3.2
Requires-Dist: djangorestframework >= 3.10.3
Requires-Dist: pytest ; extra == "test"
Requires-Dist: pytest-django ; extra == "test"
Requires-Dist: pytest-cov ; extra == "test"
Requires-Dist: flake8 ; extra == "test"
Project-URL: Source, https://github.com/simlist/django-rest-framework-emailuser
Provides-Extra: test
